awsrole/__init__.py
awsrole/awsrole.py
awsrole-0.0.2.dist-info/METADATA
awsrole-0.0.2.dist-info/WHEEL
awsrole-0.0.2.dist-info/entry_points.txt
awsrole-0.0.2.dist-info/licenses/LICENSE
awsrole-0.0.2.dist-info/RECORD
