Metadata-Version: 2.3
Name: awsrole
Version: 0.0.2
Summary: Generate temporary login link and envvars for AWS IAM Role
Project-URL: Homepage, https://github.com/gtie/awsrole
Project-URL: Issues, https://github.com/gtie/awsrole/issues
Author-email: gtie <awsrole@morp.org>
License-File: LICENSE
Classifier: License :: OSI Approved :: MIT License
Classifier: Operating System :: OS Independent
Classifier: Programming Language :: Python :: 3
Requires-Python: >=3.8
Requires-Dist: boto3
